Kuat/__init__.py
latihan_api_cihuy-0.1.0.dist-info/METADATA
latihan_api_cihuy-0.1.0.dist-info/WHEEL
latihan_api_cihuy-0.1.0.dist-info/top_level.txt
latihan_api_cihuy-0.1.0.dist-info/RECORD
